{
  "updatedAt": "2026-07-14 20:31",
  "source": "浙江省台风路径实时发布系统",
  "sourceUrl": "https://typhoon.slt.zj.gov.cn/",
  "typhoons": [
    {
      "name": "巴威",
      "enName": "BAVI",
      "code": "2609",
      "level": "热带风暴（8级）",
      "summary": "预报路径详见路径图，请以官方逐时发布为准。",
      "nearCoast": false,
      "now": {
        "windLevel": 8,
        "windSpeed": 18,
        "pressure": 992,
        "moveDir": "东北东",
        "moveSpeed": 39,
        "r7": 250,
        "r10": null,
        "position": "中心位于北纬 38.4 度、东经 124.8 度",
        "time": "07-14 19时"
      },
      "track": [
        {
          "t": "07-02 08时",
          "lat": 11,
          "lng": 160.1,
          "wind": 8,
          "strong": "热带风暴",
          "phase": "past"
        },
        {
          "t": "07-03 23时",
          "lat": 12.7,
          "lng": 152.8,
          "wind": 15,
          "strong": "强台风",
          "phase": "past"
        },
        {
          "t": "07-05 14时",
          "lat": 13.4,
          "lng": 148.2,
          "wind": 18,
          "strong": "超强台风",
          "phase": "past"
        },
        {
          "t": "07-07 02时",
          "lat": 15.8,
          "lng": 141.2,
          "wind": 18,
          "strong": "超强台风",
          "phase": "past"
        },
        {
          "t": "07-08 17时",
          "lat": 17.1,
          "lng": 132.5,
          "wind": 17,
          "strong": "超强台风",
          "phase": "past"
        },
        {
          "t": "07-10 08时",
          "lat": 20.8,
          "lng": 127.6,
          "wind": 14,
          "strong": "强台风",
          "phase": "past"
        },
        {
          "t": "07-11 01时",
          "lat": 23.5,
          "lng": 125.5,
          "wind": 14,
          "strong": "强台风",
          "phase": "past"
        },
        {
          "t": "07-11 13时",
          "lat": 26.4,
          "lng": 123.6,
          "wind": 13,
          "strong": "台风",
          "phase": "past"
        },
        {
          "t": "07-12 02时",
          "lat": 28.6,
          "lng": 120.6,
          "wind": 12,
          "strong": "台风",
          "phase": "past"
        },
        {
          "t": "07-12 15时",
          "lat": 31.2,
          "lng": 118.5,
          "wind": 9,
          "strong": "热带风暴",
          "phase": "past"
        },
        {
          "t": "07-13 04时",
          "lat": 32.8,
          "lng": 117.8,
          "wind": 8,
          "strong": "热带风暴",
          "phase": "past"
        },
        {
          "t": "07-13 16时",
          "lat": 34.3,
          "lng": 118.3,
          "wind": 8,
          "strong": "热带风暴",
          "phase": "past"
        },
        {
          "t": "07-14 05时",
          "lat": 36.3,
          "lng": 120.1,
          "wind": 8,
          "strong": "热带风暴",
          "phase": "past"
        },
        {
          "t": "07-14 18时",
          "lat": 38.2,
          "lng": 124.1,
          "wind": 8,
          "strong": "热带风暴",
          "phase": "past"
        },
        {
          "t": "07-14 19时",
          "lat": 38.4,
          "lng": 124.8,
          "wind": 8,
          "strong": "热带风暴",
          "phase": "now"
        },
        {
          "t": "07-15 01时",
          "lat": 39.57,
          "lng": 127.67,
          "wind": 7,
          "strong": "热带低压",
          "phase": "forecast"
        }
      ]
    }
  ]
}
